themis/__init__.py
themis/__main__.py
themis/backend/__init__.py
themis/backend/__main__.py
themis/backend/network.py
themis/backend/worker/__init__.py
themis/backend/worker/__main__.py
themis/backend/worker/finisher.py
themis/backend/worker/network.py
themis/backend/worker/prepper.py
themis/backend/worker/schedulers.py
themis/backend/worker/utils.py
themis/database/__init__.py
themis/database/sqlitedb.py
themis/database/statusstore.py
themis/database/utils.py
themis/laf.py
themis/resource/__init__.py
themis/resource/allocators.py
themis/resource/executors.py
themis/runtime.py
themis/user_utils.py
themis/utils.py
themis/versions.py
llnl_themis-1.2.0.dist-info/LICENSE
llnl_themis-1.2.0.dist-info/METADATA
llnl_themis-1.2.0.dist-info/NOTICE
llnl_themis-1.2.0.dist-info/WHEEL
llnl_themis-1.2.0.dist-info/entry_points.txt
llnl_themis-1.2.0.dist-info/RECORD
