Metadata-Version: 2.1
Name: llnl-themis
Version: 1.2.0
Summary: A Python-based scientific workflow ensemble manager for running concurrent UQ simulations on high-performance computers.
Home-page: https://github.com/llnl/themis
License: BSD 3-Clause License
Author: David Domyancic
Author-email: domyancic1@llnl.gov
Maintainer: David Domyancic
Maintainer-email: domyancic1@llnl.gov
Requires-Python: >=3.6
Classifier: Development Status :: 5 - Production/Stable
Classifier: Intended Audience :: Developers
Classifier: Intended Audience :: Education
Classifier: Intended Audience :: Science/Research
Classifier: License :: Other/Proprietary License
Classifier: Operating System :: OS Independent
Classifier: Programming Language :: Python :: 3
Classifier: Programming Language :: Python :: 3.6
Classifier: Programming Language :: Python :: 3.7
Classifier: Programming Language :: Python :: 3.8
Classifier: Programming Language :: Python :: 3.9
Classifier: Programming Language :: Python :: 3.10
Classifier: Programming Language :: Python :: 3.11
Classifier: Programming Language :: Python :: 3.12
Classifier: Topic :: Scientific/Engineering
Classifier: Topic :: Scientific/Engineering :: Mathematics
Requires-Dist: matplotlib
Requires-Dist: networkx
Requires-Dist: numpy
Requires-Dist: pandas
Requires-Dist: scikit-learn
Requires-Dist: scipy
Project-URL: Bug Tracker, https://github.com/LLNL/themis/issues
Project-URL: Documentation, https://llnl-themis.readthedocs.io/
Project-URL: Discussions, https://github.com/LLNL/themis/discussions
